kogger/__init__.py
kogger/logger.py
kogger-0.1.4.dist-info/LICENSE
kogger-0.1.4.dist-info/METADATA
kogger-0.1.4.dist-info/WHEEL
kogger-0.1.4.dist-info/top_level.txt
kogger-0.1.4.dist-info/RECORD
