Metadata-Version: 2.1
Name: kogger
Version: 0.1.4
Summary: A very simple logger.
Home-page: https://github.com/zengbocheng/kogger.git
Author: bochengz
Author-email: bochengzeng@bochengz.top
License: MIT
Classifier: Programming Language :: Python :: 3
Classifier: License :: OSI Approved :: MIT License
Classifier: Operating System :: OS Independent
License-File: LICENSE
